cbr_shared/__init__.py
cbr_shared/aws/__init__.py
cbr_shared/aws/s3/S3_DB_Base.py
cbr_shared/aws/s3/S3_DB_Base__Disabled.py
cbr_shared/aws/s3/S3__Files_Metadata.py
cbr_shared/aws/s3/S3__Key_Generator.py
cbr_shared/aws/s3/__init__.py
cbr_shared/cbr_backend/__init__.py
cbr_shared/cbr_backend/cbr/S3_DB__CBR.py
cbr_shared/cbr_backend/cbr/__init__.py
cbr_shared/cbr_backend/chat_threads__legacy/S3_DB__Chat_Threads.py
cbr_shared/cbr_backend/chat_threads__legacy/S3_DB__Chat_Threads__Disabled.py
cbr_shared/cbr_backend/chat_threads__legacy/S3__Chat_Threads.py
cbr_shared/cbr_backend/chat_threads__legacy/S3__Key__Chat_Thread.py
cbr_shared/cbr_backend/chat_threads__legacy/__init__.py
cbr_shared/cbr_backend/files/Model__User__File__Config.py
cbr_shared/cbr_backend/files/Model__User__File__Data.py
cbr_shared/cbr_backend/files/User__File.py
cbr_shared/cbr_backend/files/User__File__System.py
cbr_shared/cbr_backend/files/__init__.py
cbr_shared/cbr_backend/folders/Temp_Folder_Structure__Generator.py
cbr_shared/cbr_backend/folders/Temp_Folders_Structure.py
cbr_shared/cbr_backend/folders/User__Folders.py
cbr_shared/cbr_backend/folders/User__Folders__JSON_View.py
cbr_shared/cbr_backend/folders/User__Folders__Operations.py
cbr_shared/cbr_backend/folders/User__Folders__Structure.py
cbr_shared/cbr_backend/folders/User__Folders__Tree_View.py
cbr_shared/cbr_backend/folders/__init__.py
cbr_shared/cbr_backend/folders/models/Model__User__Folder.py
cbr_shared/cbr_backend/folders/models/Model__User__Folder__File.py
cbr_shared/cbr_backend/folders/models/Model__User__Folder__JSON_Base.py
cbr_shared/cbr_backend/folders/models/Model__User__Folder__JSON_File.py
cbr_shared/cbr_backend/folders/models/Model__User__Folder__JSON_Folder.py
cbr_shared/cbr_backend/folders/models/Model__User__Folder__Metadata.py
cbr_shared/cbr_backend/folders/models/Model__User__Folder__System_Files.py
cbr_shared/cbr_backend/folders/models/Model__User__Folders__JSON_Flat.py
cbr_shared-0.3.74.dist-info/LICENSE
cbr_shared-0.3.74.dist-info/METADATA
cbr_shared-0.3.74.dist-info/WHEEL
cbr_shared-0.3.74.dist-info/RECORD
