Metadata-Version: 2.3
Name: cbr_shared
Version: 0.3.74
Summary: CBR - Shared
License: MIT
Author: Dinis Cruz
Author-email: dinis.cruz@owasp.org
Requires-Python: >=3.11,<4.0
Classifier: License :: OSI Approved :: MIT License
Classifier: Programming Language :: Python :: 3
Classifier: Programming Language :: Python :: 3.11
Classifier: Programming Language :: Python :: 3.12
Classifier: Programming Language :: Python :: 3.13
Requires-Dist: cbr-content
Requires-Dist: osbot-aws
Requires-Dist: osbot-fast-api
Requires-Dist: osbot-local-stack
Requires-Dist: osbot-utils
Project-URL: Homepage, https://github.com/the-cyber-boardroom/cbr-shared
Project-URL: Repository, https://github.com/the-cyber-boardroom/cbr-shared
